gpmap/__init__.py
gpmap/__version__.py
gpmap/errors.py
gpmap/gpm.py
gpmap/stats.py
gpmap/utils.py
gpmap/simulate/__init__.py
gpmap/simulate/base.py
gpmap/simulate/fuji.py
gpmap/simulate/hoc.py
gpmap/simulate/mask.py
gpmap/simulate/multipeak_fuji.py
gpmap/simulate/nk.py
gpmap/simulate/random.py
gpmap/tests/__init__.py
gpmap/tests/test_gpm.py
gpmap/tests/test_utils.py
gpmap/tests/data/test_data.json
gpmap-0.7.0.dist-info/METADATA
gpmap-0.7.0.dist-info/WHEEL
gpmap-0.7.0.dist-info/top_level.txt
gpmap-0.7.0.dist-info/RECORD
