Metadata-Version: 2.1
Name: gpmap
Version: 0.7.0
Summary: A Python API for managing genotype-phenotype map data
Home-page: https://github.com/harmslab/gpmap
Author: Zachary R. Sailer
Author-email: zachsailer@gmail.com
License: MIT
Platform: UNKNOWN
Classifier: License :: OSI Approved :: MIT License
Classifier: Programming Language :: Python
Classifier: Programming Language :: Python :: 3
Classifier: Programming Language :: Python :: 3.6
Classifier: Programming Language :: Python :: Implementation :: CPython
Classifier: Programming Language :: Python :: Implementation :: PyPy
Requires-Python: >=3.3.0
Requires-Dist: numpy
Requires-Dist: scipy
Requires-Dist: pandas (>=0.24.2)
